agent_observe/__init__.py
agent_observe/cli.py
agent_observe/config.py
agent_observe/context.py
agent_observe/decorators.py
agent_observe/hashing.py
agent_observe/metrics.py
agent_observe/observe.py
agent_observe/pii.py
agent_observe/policy.py
agent_observe/py.typed
agent_observe/replay.py
agent_observe/hooks/__init__.py
agent_observe/hooks/circuit_breaker.py
agent_observe/hooks/context.py
agent_observe/hooks/registry.py
agent_observe/hooks/result.py
agent_observe/hooks/testing.py
agent_observe/sinks/__init__.py
agent_observe/sinks/base.py
agent_observe/sinks/jsonl_sink.py
agent_observe/sinks/otel_sink.py
agent_observe/sinks/postgres_sink.py
agent_observe/sinks/sqlite_sink.py
agent_observe/viewer/__init__.py
agent_observe/viewer/app.py
agent_observe/viewer/templates/base.html
agent_observe/viewer/templates/run_detail.html
agent_observe/viewer/templates/runs.html
agent_observe-0.2.0.dist-info/METADATA
agent_observe-0.2.0.dist-info/WHEEL
agent_observe-0.2.0.dist-info/entry_points.txt
agent_observe-0.2.0.dist-info/licenses/LICENSE
agent_observe-0.2.0.dist-info/RECORD
