Metadata-Version: 2.4
Name: agent-observe
Version: 0.2.0
Summary: Framework-agnostic observability, audit, and eval for AI agent applications
Project-URL: Homepage, https://github.com/junjieteoh/agent-observe
Project-URL: Documentation, https://github.com/junjieteoh/agent-observe#readme
Project-URL: Repository, https://github.com/junjieteoh/agent-observe
Project-URL: Issues, https://github.com/junjieteoh/agent-observe/issues
Author-email: Junjie Teoh <junjieteoh@gmail.com>
License-Expression: MIT
License-File: LICENSE
Keywords: agents,audit,enterprise,eval,guardrails,llm,observability,safety,tracing
Classifier: Development Status :: 4 - Beta
Classifier: Intended Audience :: Developers
Classifier: License :: OSI Approved :: MIT License
Classifier: Operating System :: OS Independent
Classifier: Programming Language :: Python :: 3
Classifier: Programming Language :: Python :: 3.9
Classifier: Programming Language :: Python :: 3.10
Classifier: Programming Language :: Python :: 3.11
Classifier: Programming Language :: Python :: 3.12
Classifier: Topic :: Software Development :: Libraries :: Python Modules
Classifier: Topic :: System :: Monitoring
Classifier: Typing :: Typed
Requires-Python: >=3.9
Requires-Dist: pyyaml>=6.0
Requires-Dist: typing-extensions>=4.0; python_version < '3.11'
Provides-Extra: all
Requires-Dist: fastapi>=0.100.0; extra == 'all'
Requires-Dist: jinja2>=3.1.0; extra == 'all'
Requires-Dist: mypy>=1.0.0; extra == 'all'
Requires-Dist: opentelemetry-api>=1.20.0; extra == 'all'
Requires-Dist: opentelemetry-exporter-otlp>=1.20.0; extra == 'all'
Requires-Dist: opentelemetry-sdk>=1.20.0; extra == 'all'
Requires-Dist: psycopg>=3.1.0; extra == 'all'
Requires-Dist: pytest-asyncio>=0.21.0; extra == 'all'
Requires-Dist: pytest-cov>=4.0.0; extra == 'all'
Requires-Dist: pytest>=7.0.0; extra == 'all'
Requires-Dist: ruff>=0.1.0; extra == 'all'
Requires-Dist: types-pyyaml>=6.0.0; extra == 'all'
Requires-Dist: uvicorn[standard]>=0.20.0; extra == 'all'
Provides-Extra: dev
Requires-Dist: mypy>=1.0.0; extra == 'dev'
Requires-Dist: pytest-asyncio>=0.21.0; extra == 'dev'
Requires-Dist: pytest-cov>=4.0.0; extra == 'dev'
Requires-Dist: pytest>=7.0.0; extra == 'dev'
Requires-Dist: ruff>=0.1.0; extra == 'dev'
Requires-Dist: types-pyyaml>=6.0.0; extra == 'dev'
Provides-Extra: otlp
Requires-Dist: opentelemetry-api>=1.20.0; extra == 'otlp'
Requires-Dist: opentelemetry-exporter-otlp>=1.20.0; extra == 'otlp'
Requires-Dist: opentelemetry-sdk>=1.20.0; extra == 'otlp'
Provides-Extra: postgres
Requires-Dist: psycopg>=3.1.0; extra == 'postgres'
Provides-Extra: viewer
Requires-Dist: fastapi>=0.100.0; extra == 'viewer'
Requires-Dist: jinja2>=3.1.0; extra == 'viewer'
Requires-Dist: uvicorn[standard]>=0.20.0; extra == 'viewer'
